{
  "data": [
    {
      "title": "Will It Mythos?",
      "hot": "3.0m",
      "desc": "swelljoe.com",
      "source": "tech",
      "tag": "⬆️ 62 points",
      "url": "https://swelljoe.com/post/will-it-mythos/"
    },
    {
      "title": "Steam Machine launches today",
      "hot": "3.0m",
      "desc": "store.steampowered.com",
      "source": "tech",
      "tag": "⬆️ 1387 points",
      "url": "https://store.steampowered.com/news/group/45479024/view/685257114654870245"
    },
    {
      "title": "VibeThinker: 3B param model that beats Opus 4.5 on reasoning with novel SFT+GRPO",
      "hot": "3.0m",
      "desc": "arxiv.org",
      "source": "tech",
      "tag": "⬆️ 88 points",
      "url": "https://arxiv.org/abs/2606.16140"
    },
    {
      "title": "GLM-5.2 – How to Run Locally",
      "hot": "3.0m",
      "desc": "unsloth.ai",
      "source": "tech",
      "tag": "⬆️ 286 points",
      "url": "https://unsloth.ai/docs/models/glm-5.2"
    },
    {
      "title": "Polymarket has flooded social media with deceptive videos by paid creators",
      "hot": "2.9m",
      "desc": "wsj.com",
      "source": "tech",
      "tag": "⬆️ 132 points",
      "url": "https://www.wsj.com/business/media/polymarket-social-media-bets-prediction-market-441cdeb5?st=HhTZY2"
    },
    {
      "title": "In praise of memcached",
      "hot": "2.9m",
      "desc": "jchri.st",
      "source": "tech",
      "tag": "⬆️ 95 points",
      "url": "https://jchri.st/blog/in-praise-of-memcached/"
    },
    {
      "title": "An Introduction to YOLO26",
      "hot": "2.9m",
      "desc": "blog.roboflow.com",
      "source": "tech",
      "tag": "⬆️ 39 points",
      "url": "https://blog.roboflow.com/yolo26/"
    },
    {
      "title": "Optocam Zero: a Pi Zero based digital camera made using off the shelf components",
      "hot": "2.9m",
      "desc": "github.com",
      "source": "tech",
      "tag": "⬆️ 137 points",
      "url": "https://github.com/dorukkumkumoglu/optocamzero"
    },
    {
      "title": "Japanese symbols that speak without words",
      "hot": "2.9m",
      "desc": "arun.is",
      "source": "tech",
      "tag": "⬆️ 148 points",
      "url": "https://arun.is/blog/japan-symbols/"
    },
    {
      "title": "Cyberdecks, going analog, and convivial technology",
      "hot": "2.9m",
      "desc": "blog.hydroponictrash.solar",
      "source": "tech",
      "tag": "⬆️ 77 points",
      "url": "https://blog.hydroponictrash.solar/cyberdecks-going-analog-and-convivial-technology/"
    },
    {
      "title": "My Mathematical Regression",
      "hot": "2.9m",
      "desc": "blog.dahl.dev",
      "source": "tech",
      "tag": "⬆️ 252 points",
      "url": "https://blog.dahl.dev/posts/my-mathematical-regression/"
    },
    {
      "title": "Package Managers need global hooks",
      "hot": "2.8m",
      "desc": "captnemo.in",
      "source": "tech",
      "tag": "⬆️ 13 points",
      "url": "https://captnemo.in/blog/2026/06/17/package-managers-need-hooks/"
    },
    {
      "title": "Moebius: 0.2B image inpainting model with 10B-level performance",
      "hot": "2.8m",
      "desc": "hustvl.github.io",
      "source": "tech",
      "tag": "⬆️ 261 points",
      "url": "https://hustvl.github.io/Moebius/"
    },
    {
      "title": "Giant Banana Pulled Over: Driver Says Cops Have Stopped Him 100s of Times",
      "hot": "2.8m",
      "desc": "cowboystatedaily.com",
      "source": "tech",
      "tag": "⬆️ 31 points",
      "url": "https://cowboystatedaily.com/2026/06/18/giant-banana-pulled-over-in-montana-driver-says-cops-have-stopped-him-100s-of-times/"
    },
    {
      "title": "Windows NT for GameCube/Wii",
      "hot": "2.8m",
      "desc": "github.com",
      "source": "tech",
      "tag": "⬆️ 42 points",
      "url": "https://github.com/Wack0/entii-for-workcubes"
    },
    {
      "title": "Show HN: Oak – Git alternative designed for agents",
      "hot": "2.8m",
      "desc": "oak.space",
      "source": "tech",
      "tag": "⬆️ 171 points",
      "url": "https://oak.space/oak/oak"
    },
    {
      "title": "Canada plans 'nuclear renaissance' with up to 10 reactors built by 2040",
      "hot": "2.8m",
      "desc": "cbc.ca",
      "source": "tech",
      "tag": "⬆️ 402 points",
      "url": "https://www.cbc.ca/news/politics/federal-nuclear-strategy-9.7244509"
    },
    {
      "title": "1,700 free online courses from top universities",
      "hot": "2.7m",
      "desc": "openculture.com",
      "source": "tech",
      "tag": "⬆️ 125 points",
      "url": "https://www.openculture.com/freeonlinecourses"
    },
    {
      "title": "Canyon HUD helmet for road riding",
      "hot": "2.7m",
      "desc": "media-centre.canyon.com",
      "source": "tech",
      "tag": "⬆️ 84 points",
      "url": "https://media-centre.canyon.com/en-INT/266866-new-canyon-heads-up-display-helmet-could-be-a-safety-gamechanger-for-road-riding/"
    },
    {
      "title": "Is it time for a new Embedded Linux build system?",
      "hot": "2.7m",
      "desc": "yoebuild.org",
      "source": "tech",
      "tag": "⬆️ 60 points",
      "url": "https://yoebuild.org/blog/time-for-a-new-build-system/"
    }
  ],
  "updatedAt": "2026-06-23T05:34:25.567Z"
}