{
  "data": [
    {
      "title": "The Cypherpunk Library",
      "hot": "3.0m",
      "desc": "cypherpunkbooks.com",
      "source": "tech",
      "tag": "⬆️ 132 points",
      "url": "https://www.cypherpunkbooks.com"
    },
    {
      "title": "Dopamine Fracking",
      "hot": "3.0m",
      "desc": "igerman.cc",
      "source": "tech",
      "tag": "⬆️ 420 points",
      "url": "https://igerman.cc/blog/dopamine-fracking/"
    },
    {
      "title": "1k Data Breaches Later, the Disclosure Lag Is Worse",
      "hot": "3.0m",
      "desc": "troyhunt.com",
      "source": "tech",
      "tag": "⬆️ 181 points",
      "url": "https://www.troyhunt.com/1000-data-breaches-later-the-disclosure-lag-is-worse-than-ever/"
    },
    {
      "title": "A Family Project (2022)",
      "hot": "3.0m",
      "desc": "bittersoutherner.com",
      "source": "tech",
      "tag": "⬆️ 41 points",
      "url": "https://bittersoutherner.com/feature/2022/a-family-project"
    },
    {
      "title": "Building from zero after addiction, prison, and a felony",
      "hot": "2.9m",
      "desc": "gavinray97.github.io",
      "source": "tech",
      "tag": "⬆️ 689 points",
      "url": "https://gavinray97.github.io/blog/building-from-zero-after-addiction-prison-felony"
    },
    {
      "title": "Spherical Voronoi Diagram",
      "hot": "2.9m",
      "desc": "jasondavies.com",
      "source": "tech",
      "tag": "⬆️ 33 points",
      "url": "https://www.jasondavies.com/maps/voronoi/"
    },
    {
      "title": "APC–2 – A professional record cutter for producing original playback discs",
      "hot": "2.9m",
      "desc": "teenage.engineering",
      "source": "tech",
      "tag": "⬆️ 230 points",
      "url": "https://teenage.engineering/products/apc-2"
    },
    {
      "title": "How much of Thermo Fisher's antibody data has been manipulated?",
      "hot": "2.9m",
      "desc": "reeserichardson.blog",
      "source": "tech",
      "tag": "⬆️ 56 points",
      "url": "https://reeserichardson.blog/2026/05/28/how-much-of-thermo-fishers-antibody-data-has-been-manipulated/"
    },
    {
      "title": "Zig Structs of Arrays (2024)",
      "hot": "2.9m",
      "desc": "andreashohmann.com",
      "source": "tech",
      "tag": "⬆️ 16 points",
      "url": "https://andreashohmann.com/zig-struct-of-arrays/"
    },
    {
      "title": "Richard Scolyer Has Died",
      "hot": "2.9m",
      "desc": "bbc.com",
      "source": "tech",
      "tag": "⬆️ 89 points",
      "url": "https://www.bbc.com/news/articles/c14yz5jg476o"
    },
    {
      "title": "The Smallest Brain You Can Build: A Perceptron in Python",
      "hot": "2.9m",
      "desc": "ranpara.net",
      "source": "tech",
      "tag": "⬆️ 214 points",
      "url": "https://ranpara.net/posts/perceptron-explained-from-scratch/"
    },
    {
      "title": "Playing with Vision Embeddings",
      "hot": "2.8m",
      "desc": "prestonbjensen.com",
      "source": "tech",
      "tag": "⬆️ 79 points",
      "url": "https://prestonbjensen.com/posts/playing-with-vision-embeddings"
    },
    {
      "title": "Config Files That Run Code: Supply Chain Security Blindspot",
      "hot": "2.8m",
      "desc": "safedep.io",
      "source": "tech",
      "tag": "⬆️ 11 points",
      "url": "https://safedep.io/config-files-that-run-code/"
    },
    {
      "title": "Amber Tree: A Middle Ground Between Rowan Red and Green Trees",
      "hot": "2.8m",
      "desc": "blog.gplane.win",
      "source": "tech",
      "tag": "⬆️ 5 points",
      "url": "https://blog.gplane.win/posts/introducing-amber-tree.html"
    },
    {
      "title": "OneDrive data now has an expiry date",
      "hot": "2.8m",
      "desc": "ms365news.com",
      "source": "tech",
      "tag": "⬆️ 96 points",
      "url": "https://ms365news.com/blogs/f/your-onedrive-data-now-has-an-expiry-data"
    },
    {
      "title": "The EU Open Source Strategy",
      "hot": "2.8m",
      "desc": "digital-strategy.ec.europa.eu",
      "source": "tech",
      "tag": "⬆️ 98 points",
      "url": "https://digital-strategy.ec.europa.eu/en/policies/open-source-strategy"
    },
    {
      "title": "New drug 'functionally cures' many hepatitis B virus infections",
      "hot": "2.8m",
      "desc": "science.org",
      "source": "tech",
      "tag": "⬆️ 198 points",
      "url": "https://www.science.org/content/article/new-drug-functionally-cures-many-hepatitis-b-virus-infections?user_id=66c4bf745d78644b3aa57b08"
    },
    {
      "title": "Algorithmic Monocultures in Hiring",
      "hot": "2.7m",
      "desc": "algorithmichiring.github.io",
      "source": "tech",
      "tag": "⬆️ 114 points",
      "url": "https://algorithmichiring.github.io/"
    },
    {
      "title": "Making peace with your unlived dreams (2023)",
      "hot": "2.7m",
      "desc": "nik.art",
      "source": "tech",
      "tag": "⬆️ 252 points",
      "url": "https://nik.art/making-peace-with-your-unlived-dreams/"
    },
    {
      "title": "Tiny hackable CUDA language model implementation",
      "hot": "2.7m",
      "desc": "github.com",
      "source": "tech",
      "tag": "⬆️ 39 points",
      "url": "https://github.com/markusheimerl/gpt"
    }
  ],
  "updatedAt": "2026-06-08T12:11:42.150Z"
}